openglider_cpp.cp38-win_amd64.pyd
freecad/freecad_glider/__init__.py
freecad/freecad_glider/glider_commands.py
freecad/freecad_glider/glider_metadata.py
freecad/freecad_glider/init.py
freecad/freecad_glider/init_gui.py
freecad/freecad_glider/profiling.py
freecad/freecad_glider/data/default_glider2d.json
freecad/freecad_glider/data/glider2d.json
freecad/freecad_glider/data/glider2d_1.json
freecad/freecad_glider/icons/airfoil_command.svg
freecad/freecad_glider/icons/airfoil_merge_command.svg
freecad/freecad_glider/icons/aoa_command.svg
freecad/freecad_glider/icons/arc_command.svg
freecad/freecad_glider/icons/attach_command.svg
freecad/freecad_glider/icons/ballooning_command.svg
freecad/freecad_glider/icons/ballooning_feature.svg
freecad/freecad_glider/icons/ballooning_merge_command.svg
freecad/freecad_glider/icons/cell_command.svg
freecad/freecad_glider/icons/color_selector.svg
freecad/freecad_glider/icons/colors.svg
freecad/freecad_glider/icons/cut_command.svg
freecad/freecad_glider/icons/design_command.svg
freecad/freecad_glider/icons/dxf_command.svg
freecad/freecad_glider/icons/feature.svg
freecad/freecad_glider/icons/flap_feature.svg
freecad/freecad_glider/icons/freecad_color.gpl
freecad/freecad_glider/icons/gl2d_export.svg
freecad/freecad_glider/icons/glider_workbench.svg
freecad/freecad_glider/icons/hole_feature.svg
freecad/freecad_glider/icons/import_glider.svg
freecad/freecad_glider/icons/line_command.svg
freecad/freecad_glider/icons/line_observe.svg
freecad/freecad_glider/icons/new_glider.svg
freecad/freecad_glider/icons/panel_method.svg
freecad/freecad_glider/icons/pattern_command.svg
freecad/freecad_glider/icons/polar.svg
freecad/freecad_glider/icons/preferences-glider.svg
freecad/freecad_glider/icons/refresh_command.svg
freecad/freecad_glider/icons/rib_feature.svg
freecad/freecad_glider/icons/scale_feature.svg
freecad/freecad_glider/icons/shape_command.svg
freecad/freecad_glider/icons/sharknose_feature.svg
OpenGlider-0.0.6.dist-info/LICENSE
OpenGlider-0.0.6.dist-info/LICENSE_HEADER
OpenGlider-0.0.6.dist-info/METADATA
OpenGlider-0.0.6.dist-info/WHEEL
OpenGlider-0.0.6.dist-info/top_level.txt
OpenGlider-0.0.6.dist-info/RECORD
