Metadata-Version: 2.1
Name: OpenGlider
Version: 0.0.6
Summary: tool for glider design
Home-page: http://openglider.org
Author: Booya
Author-email: UNKNOWN
License: GPL-v3
Download-URL: https://github.com/hiaselhans/OpenGlider/tarball/0.01dev0
Platform: UNKNOWN
Requires-Dist: svgwrite
Requires-Dist: numpy
Requires-Dist: scipy
Requires-Dist: ezdxf
Requires-Dist: ezodf
Requires-Dist: lxml
Requires-Dist: pyexcel-ods
Requires-Dist: meshpy
